schic/__init__.py
schic/main.py
schic/modules/__init__.py
schic/modules/contacts.py
schic/modules/cutadapt.py
schic/modules/extract.py
schic/modules/report.py
schic/modules/whitelist.py
schic/scripts/contacts.sh
schic/static/env.yaml
schic/utils/__init__.py
schic/utils/pairtools.py
schic/utils/umitools.py
schic-0.1.9.dist-info/METADATA
schic-0.1.9.dist-info/WHEEL
schic-0.1.9.dist-info/entry_points.txt
schic-0.1.9.dist-info/RECORD
