Metadata-Version: 2.3
Name: schic
Version: 0.1.9
Summary: single cell HiC analysis package
Author: DeYing Zhang
Author-email: legendzdy@dingtalk.com
Requires-Python: >=3.10
Classifier: Programming Language :: Python :: 3
Classifier: Programming Language :: Python :: 3.10
Classifier: Programming Language :: Python :: 3.11
Classifier: Programming Language :: Python :: 3.12
Classifier: Programming Language :: Python :: 3.13
Requires-Dist: basebio (>=0.4.8)
Requires-Dist: matplotlib (>=3.10.0)
Requires-Dist: pairtools (>=1.1.2,<2.0.0)
Requires-Dist: seaborn (>=0.13.2)
Requires-Dist: typer (>=0.15.2)
Requires-Dist: umi-tools (>=1.1.6)
